octopus_api.py
octopus_api-2.1.0.dist-info/LICENSE
octopus_api-2.1.0.dist-info/WHEEL
octopus_api-2.1.0.dist-info/METADATA
octopus_api-2.1.0.dist-info/RECORD
