Metadata-Version: 2.1
Name: octopus-api
Version: 2.1.0
Summary: Octopus-api is a python library for performing client-based optimized connections requests and limit rates set by the endpoint contract.
Home-page: https://github.com/FilipByren/octopus-api
License: GNU GENERAL PUBLIC LICENSE
Keywords: rate limiting,concurrent api,python,https://docs.aiohttp.org
Author: Filip Byrén
Author-email: filip.j.byren@gmail.com
Requires-Python: >=3.7,<4.0
Classifier: License :: Other/Proprietary License
Classifier: Programming Language :: Python :: 3
Classifier: Programming Language :: Python :: 3.7
Classifier: Programming Language :: Python :: 3.8
Classifier: Programming Language :: Python :: 3.9
Requires-Dist: aiohttp (>=3.8.1,<4.0.0)
Requires-Dist: asyncio (>=3.4.3,<4.0.0)
Requires-Dist: tqdm (>=4.62.3,<5.0.0)
Project-URL: Repository, https://github.com/FilipByren/octopus-api
